[
    {
        "nombre": "Lionel",
        "apellido": "Messi",
        "idEquipo": 1,
        "genero": "Masculino",
        "dni": 123456789,
        "edad": 30,
        "division": "Mayores",
        "altura": 1.70,
        "esTitular": false,
        "deporte": "Futbol",
        "posicion": "No tiene"
    },
    {
        "nombre": "Cristiano",
        "apellido": "Ronaldo",
        "idEquipo": 1,
        "genero": "Masculino",
        "dni": 987654321,
        "edad": 31,
        "division": "Mayores",
        "altura": 1.87,
        "esTitular": false,
        "deporte": "Futbol",
        "posicion": "No tiene"
    },
    {
        "nombre": "Neymar",
        "apellido": "Jr.",
        "idEquipo": 1,
        "genero": "Masculino",
        "dni": 456789123,
        "edad": 28,
        "division": "Mayores",
        "altura": 1.75,
        "esTitular": false,
        "deporte": "Futbol",
        "posicion": "No tiene"
    },
    {
        "nombre": "Marta",
        "apellido": "Vieira da Silva",
        "idEquipo": 1,
        "genero": "Femenino",
        "dni": 321654987,
        "edad": 35,
        "division": "Mayores",
        "altura": 1.63,
        "esTitular": false,
        "deporte": "Futbol",
        "posicion": "No tiene"
    },
    {
        "nombre": "Andrés",
        "apellido": "Iniesta",
        "idEquipo": 1,
        "genero": "Masculino",
        "dni": 789123456,
        "edad": 36,
        "division": "Mayores",
        "altura": 1.70,
        "esTitular": false,
        "deporte": "Futbol",
        "posicion": "No tiene"
    },
    {
        "nombre": "Alex",
        "apellido": "Morgan",
        "idEquipo": 1,
        "genero": "Femenino",
        "dni": 654987321,
        "edad": 32,
        "division": "Mayores",
        "altura": 1.70,
        "esTitular": false,
        "deporte": "Futbol",
        "posicion": "No tiene"
    },
    {
        "nombre": "Xavi",
        "apellido": "Hernández",
        "idEquipo": 1,
        "genero": "Masculino",
        "dni": 123987456,
        "edad": 40,
        "division": "Mayores",
        "altura": 1.70,
        "esTitular": false,
        "deporte": "Futbol",
        "posicion": "No tiene"
    },
    {
        "nombre": "Carli",
        "apellido": "Lloyd",
        "idEquipo": 1,
        "genero": "Femenino",
        "dni": 987456321,
        "edad": 39,
        "division": "Mayores",
        "altura": 1.70,
        "esTitular": false,
        "deporte": "Futbol",
        "posicion": "No tiene"
    },
    {
        "nombre": "Andrés",
        "apellido": "D'Alessandro",
        "idEquipo": 1,
        "genero": "Masculino",
        "dni": 456123789,
        "edad": 39,
        "division": "Mayores",
        "altura": 1.70,
        "esTitular": false,
        "deporte": "Futbol",
        "posicion": "No tiene"
    },
    {
        "nombre": "Abby",
        "apellido": "Wambach",
        "idEquipo": 1,
        "genero": "Femenino",
        "dni": 321789654,
        "edad": 41,
        "division": "Mayores",
        "altura": 1.80,
        "esTitular": false,
        "deporte": "Futbol",
        "posicion": "No tiene"
    },
    {
        "nombre": "Luis",
        "apellido": "Suárez",
        "idEquipo": 1,
        "genero": "Masculino",
        "dni": 789456123,
        "edad": 34,
        "division": "Mayores",
        "altura": 1.82,
        "esTitular": false,
        "deporte": "Futbol",
        "posicion": "No tiene"
    },
    {
        "nombre": "Hope",
        "apellido": "Solo",
        "idEquipo": 1,
        "genero": "Femenino",
        "dni": 654321987,
        "edad": 40,
        "division": "Mayores",
        "altura": 1.75,
        "esTitular": false,
        "deporte": "Futbol",
        "posicion": "No tiene"
    }
]
